{"indicator_number":"5.5.5","sdg_goal":"5","data_non_statistical":false,"graph_title":"Enrolled in master and specialist studies by type of education","graph_type":"line","indicator_name":"Enrolled in master and specialist studies by type of education","indicator_sort_order":"05-05-05","published":true,"reporting_status":"complete","target_name":"University education (2st level)","target_id":"5.5","un_designated_tier":"5","data_show_map":false,"source_active_1":true,"source_url_text_1":"Link to source","source_active_2":false,"source_url_text_2":"Link to Source","source_active_3":false,"source_url_3":"Link to source","source_active_4":false,"source_url_text_4":"Link to source","source_active_5":false,"source_url_text_5":"Link to source","source_active_6":false,"source_url_text_6":"Link to source","title":"Untitled","source_organisation_1":"BHAS","national_indicator_description":"Enrolled student is every person enrolled at higher education institution. Second cycle studies are organized upon completion of the first cycle of studies, these last one or two years, and they are valued with 60 or 120 ECTS credits, thus reaching 300 ECTS credits together with the first cycle. The second cycle leads to the academic title of Master or equivalent.","computation_units":"Number","page_content":"","national_metadata_updated_date":"2025-03-21","national_data_updated_date":"2025-03-21","national_metadata_update_url_text":"2025-03-21: see changes on GitHub","national_metadata_update_url":"https://github.com/demootpbh/populationData-data/commit/d495f57bdb5ca062c7163d8b62356d6e533086cc","national_data_update_url_text":"2025-03-21: see changes on GitHub","national_data_update_url":"https://github.com/demootpbh/populationData-data/commit/d495f57bdb5ca062c7163d8b62356d6e533086cc","indicator":"5.5.5"}