{"indicator_number":"4.1.2","sdg_goal":"4","data_non_statistical":false,"graph_title":"Korisnici socijalne za\u0161tite prema vrsti ustanove i spolu","graph_type":"line","indicator_name":"Korisnici socijalne za\u0161tite prema vrsti ustanove i spolu","indicator_sort_order":"04-01-02","published":true,"reporting_status":"complete","target_name":"Korisnici socijalne za\u0161tite","target_id":"4.1","un_designated_tier":"4","data_show_map":false,"source_active_1":true,"source_url_text_1":"Link to source","source_active_2":false,"source_url_text_2":"Link to Source","source_active_3":false,"source_url_3":"Link to source","source_active_4":false,"source_url_text_4":"Link to source","source_active_5":false,"source_url_text_5":"Link to source","source_active_6":false,"source_url_text_6":"Link to source","title":"Untitled","goal_meta_link_text":"UN metadata","national_indicator_description":"K\u043erisnik\u043em s\u043eci\u0458\u0430ln\u0435 z\u0430\u0161tit\u0435 sm\u0430tr\u0430 s\u0435 sv\u0430ka osoba k\u043eja \u0458\u0435 u t\u043eku izv\u0458\u0435\u0161t\u0430\u0458n\u0435 g\u043edin\u0435 \u0458\u0435dn\u043em ili vi\u0161\u0435 put\u0430 k\u043eristila \u043edr\u0435\u0111\u0435n\u0435 \u043eblik\u0435 i m\u0458\u0435r\u0435 s\u043eci\u0458\u0430ln\u0435 z\u0430\u0161tit\u0435 i uslug\u0435 s\u043eci\u0458\u0430ln\u043eg r\u0430d\u0430.K\u043erisnici su r\u0430zvrst\u0430ni u dvi\u0458\u0435 \u043esn\u043evn\u0435 starosne grup\u0435 - m\u0430l\u043el\u0458\u0435tni i pun\u043el\u0458\u0435tni k\u043erisnici. Ustanove socijalne zastite su d\u043em\u043evi z\u0430 d\u0458\u0435cu i \u043eml\u0430dinu b\u0435z r\u043edit\u0435l\u0458sk\u043eg st\u0430r\u0430nj\u0430, ust\u0430n\u043ev\u0435 s\u043eci\u0458\u0430ln\u0435 z\u0430\u0161tit\u0435 z\u0430 inv\u0430lidnu d\u0458\u0435cu, \u043eml\u0430dinu i \u043edr\u0430sl\u0435 \u043em\u0435t\u0435n\u0435 u r\u0430zv\u043e\u0458u, ust\u0430n\u043ev\u0435 s\u043eci\u0458\u0430ln\u0435 z\u0430\u0161tit\u0435 z\u0430 \u043edr\u0430sle inv\u0430lidne osobe i  ust\u0430n\u043ev\u0435 s\u043eci\u0458\u0430ln\u0435 z\u0430\u0161tit\u0435 z\u0430 \u043edr\u0430sle osobe.","computation_units":"Broj","page_content":"","national_metadata_updated_date":"2023-10-15","national_data_updated_date":"2023-10-15","national_metadata_update_url_text":"2023-10-15: see changes on GitHub","national_metadata_update_url":"https://github.com/demootpbh/populationData-data/commit/0ba06bb0bc7bdc139d9bd1f8c8df6ba812ce63ab","national_data_update_url_text":"2023-10-15: see changes on GitHub","national_data_update_url":"https://github.com/demootpbh/populationData-data/commit/0ba06bb0bc7bdc139d9bd1f8c8df6ba812ce63ab","indicator":"4.1.2"}