{"data":{"Year":[2011,2012,2013,2014,2015,2016,2017,2018,2019,2020,2021,2022,2023,2011,2012,2013,2014,2015,2016,2017,2018,2019,2020,2021,2022,2023,2011,2012,2013,2014,2015,2016,2017,2018,2019,2020,2021,2022,2023],"UNIT_MEASURE":["Number","Number","Number","Number","Number","Number","Number","Number","Number","Number","Number","Number","Number","Number","Number","Number","Number","Number","Number","Number","Number","Number","Number","Number","Number","Number","Number","Number","Number","Number","Number","Number","Number","Number","Number","Number","Number","Number","Number"],"Sex":["Both sexes","Both sexes","Both sexes","Both sexes","Both sexes","Both sexes","Both sexes","Both sexes","Both sexes","Both sexes","Both sexes","Both sexes","Both sexes","M","M","M","M","M","M","M","M","M","M","M","M","M","F","F","F","F","F","F","F","F","F","F","F","F","F"],"Value":[316657,304881,302133,296819,291342,287729,282946,280018,274034,268059,264802,260337,256343,162596,156296,154895,152363,149888,148250,145441,143837,140792,137540,136347,133629,131701,154061,148585,147238,144456,141454,139479,137505,136181,133242,130519,128455,126708,124642]},"edges":[]}